motorcontrollib/Motors.cpython-37m-arm-linux-gnueabihf.so
motorcontrollib/__init__.py
motorcontrollib-0.1.0.dist-info/LICENSE
motorcontrollib-0.1.0.dist-info/METADATA
motorcontrollib-0.1.0.dist-info/WHEEL
motorcontrollib-0.1.0.dist-info/top_level.txt
motorcontrollib-0.1.0.dist-info/RECORD
