Metadata-Version: 2.1
Name: motorcontrollib
Version: 0.1.0
Summary: A Motor Control Library for Python
Home-page: https://github.com/wDove1/Motor-Control-Python
Author: William Dove
Author-email: williamtdove@gmail.com
License: Apache License 2.0
Platform: UNKNOWN
Classifier: Programming Language :: Python :: 3
Classifier: License :: OSI Approved :: Apache Software License
Classifier: Operating System :: OS Independent
Requires-Python: >=3.7
